ssh_key_mgr/__init__.py
ssh_key_mgr/__main__.py
ssh_key_mgr/b64.py
ssh_key_mgr/keys.py
ssh_key_mgr/pem.py
ssh_key_mgr/py.typed
ssh_key_mgr/secretstr.py
ssh_key_mgr/utils.py
ssh_key_mgr/cli/app.py
ssh_key_mgr/openssh/__init__.py
ssh_key_mgr/openssh/file.py
ssh_key_mgr/openssh/keys.py
ssh_key_mgr/openssh/encryption/__init__.py
ssh_key_mgr/openssh/encryption/enc_aes256_ctr_bcrypt.py
ssh_key_mgr/openssh/encryption/enc_plain.py
ssh_key_mgr/openssh/encryption/aes/__init__.py
ssh_key_mgr/openssh/encryption/aes/base.py
ssh_key_mgr/openssh/encryption/aes/impl.py
ssh_key_mgr/openssh/encryption/bcrypt/__init__.py
ssh_key_mgr/openssh/encryption/bcrypt/base.py
ssh_key_mgr/openssh/encryption/bcrypt/impl.py
ssh_key_mgr/putty/__init__.py
ssh_key_mgr/putty/checksum.py
ssh_key_mgr/putty/file.py
ssh_key_mgr/putty/keys.py
ssh_key_mgr/putty/encryption/__init__.py
ssh_key_mgr/putty/encryption/aes/__init__.py
ssh_key_mgr/putty/encryption/aes/base.py
ssh_key_mgr/putty/encryption/aes/impl.py
ssh_key_mgr/putty/encryption/argon/__init__.py
ssh_key_mgr/putty/encryption/argon/base.py
ssh_key_mgr/putty/encryption/argon/impl.py
ssh_key_mgr/putty/ppk/__init__.py
ssh_key_mgr/putty/ppk/base.py
ssh_key_mgr/putty/ppk/file.py
ssh_key_mgr/putty/ppk/stream.py
ssh_key_mgr-0.1.4.dist-info/METADATA
ssh_key_mgr-0.1.4.dist-info/WHEEL
ssh_key_mgr-0.1.4.dist-info/entry_points.txt
ssh_key_mgr-0.1.4.dist-info/licenses/LICENSE
ssh_key_mgr-0.1.4.dist-info/RECORD
